scrapy_fake_useragent/__init__.py
scrapy_fake_useragent/middleware.py
scrapy_fake_useragent/providers.py
scrapy_fake_useragent-1.4.3.dist-info/LICENSE.txt
scrapy_fake_useragent-1.4.3.dist-info/METADATA
scrapy_fake_useragent-1.4.3.dist-info/WHEEL
scrapy_fake_useragent-1.4.3.dist-info/top_level.txt
scrapy_fake_useragent-1.4.3.dist-info/RECORD
