Metadata-Version: 2.1
Name: scrapy-fake-useragent
Version: 1.4.3
Summary: Use a random User-Agent provided by fake-useragent for every request
Home-page: https://github.com/alecxe/scrapy-fake-useragent
Author: Alexander Afanasyev
Author-email: me@alecxe.me
Maintainer: Alexander Afanasyev
Maintainer-email: me@alecxe.me
License: New BSD License
Keywords: scrapy proxy user-agent web-scraping
Platform: UNKNOWN
Classifier: Development Status :: 5 - Production/Stable
Classifier: Framework :: Scrapy
Classifier: Intended Audience :: Developers
Classifier: License :: OSI Approved :: MIT License
Classifier: Programming Language :: Python
Classifier: Programming Language :: Python :: 3
Classifier: Programming Language :: Python :: 3.5
Classifier: Programming Language :: Python :: 3.6
Classifier: Programming Language :: Python :: 3.7
Classifier: Programming Language :: Python :: 3.8
Classifier: Topic :: Internet :: WWW/HTTP
Requires-Python: >=3.5
Requires-Dist: fake-useragent
Requires-Dist: faker
